pou/__init__.py
pou/__main__.py
pou/core/__init__.py
pou/core/sleepy_colors.py
pou/core/storage.py
pou/core/terminal.py
pou/pages/__init__.py
pou/pages/chatgpt.py
pou/pages/pou.py
pou/pages/settings.py
pou-0.0.7.dist-info/METADATA
pou-0.0.7.dist-info/WHEEL
pou-0.0.7.dist-info/top_level.txt
pou-0.0.7.dist-info/RECORD
