Metadata-Version: 2.1
Name: pou
Version: 0.0.7
Summary: A stylish, minimalistic, ChatGPT-infused command-line interface 
Author-email: hwelsters <redacted@redacted.redacted>
Project-URL: Homepage, https://github.com/hwelsters/pau
Project-URL: Bug Tracker, https://github.com/hwelsters/pau/issues
Requires-Python: >=3.0
Requires-Dist: colored (>=1.4.4)
Requires-Dist: boxing (>=0.1.4)
Requires-Dist: inquirer (>=3.1.3)
Requires-Dist: requests (>=2.26.0)
